sparclet/__init__.py
sparclet/__main__.py
sparclet/helpers.py
sparclet-1.0.1.dist-info/LICENSE
sparclet-1.0.1.dist-info/METADATA
sparclet-1.0.1.dist-info/WHEEL
sparclet-1.0.1.dist-info/top_level.txt
sparclet-1.0.1.dist-info/RECORD
