Metadata-Version: 2.1
Name: sparclet
Version: 1.0.1
Summary: A python library to generate and interact with flatmaps in a jupyter notebook using the ipyleaflet library.
Author-email: Archit Bhatnagar <archibhatnagar27@gmail.com>, Koustubh Sudarshan <koustubh.sudarshan@gmail.com>, Chloe Hoff <chloedhoff@gmail.com>
License: Copyright (c) 2018 The Python Packaging Authority        
Project-URL: Homepage, https://github.com/SPARC-FAIR-Codeathon/SPARClet
Keywords: SPARC,flatmap,leaflet
Classifier: License :: OSI Approved :: MIT License
Classifier: Programming Language :: Python :: 3
Classifier: Development Status :: 3 - Alpha
Classifier: Framework :: Jupyter
Classifier: Intended Audience :: Science/Research
Classifier: Natural Language :: English
Requires-Python: >=3.5
License-File: LICENSE
Requires-Dist: ipyleaflet
Requires-Dist: ipywidgets
Requires-Dist: bs4
Requires-Dist: requests
